reissvd_imgcompress/__init__.py
reissvd_imgcompress/reis_svd.py
reissvd_imgcompress-0.2.0.dist-info/LICENSE.txt
reissvd_imgcompress-0.2.0.dist-info/METADATA
reissvd_imgcompress-0.2.0.dist-info/WHEEL
reissvd_imgcompress-0.2.0.dist-info/top_level.txt
reissvd_imgcompress-0.2.0.dist-info/RECORD
