Metadata-Version: 2.1
Name: reissvd_imgcompress
Version: 0.2.0
Summary: Image compression using REIS-SVD with evaluation metrics like MSE, PSNR, and SSIM.
Author: Katie Wen-Ling Kuo
Author-email: katie20030705@gmail.com
License: MIT
Classifier: License :: OSI Approved :: MIT License
Classifier: Programming Language :: Python :: 3
Requires-Python: >=3.6
License-File: LICENSE.txt
Requires-Dist: numpy
Requires-Dist: Pillow
Requires-Dist: matplotlib
Requires-Dist: scipy
Requires-Dist: scikit-image
